[{"address":"0x25b8fe1de9daf8ba351890744ff28cf7dfa8f5e3","symbol":"ZRX","decimals":18,"name":"0x Protocol","trading":{"WETH":{"volume":"457.27679076","highPrice":"0.41511175","lowPrice":"1.02818864","change24Hour":"23.97","lastPrice":"0.57561175"},"DAI":{"volume":"15.27679076","highPrice":"7.41511175","lowPrice":"3.02818864","change24Hour":"23.97","lastPrice":"0.57561175"}}},{"address":"0x48bacb9266a570d521063ef5dd96e61686dbe788","symbol":"WETH","decimals":18,"name":"Ether Token","trading":{"DAI":{"volume":"457.27679076","highPrice":"0.41511175","lowPrice":"1.02818864","change24Hour":"23.97","lastPrice":"0.57561175"}}},{"address":"0x22fd79ee303e1f637a92eda438493d7bde7e287b","symbol":"STU","decimals":18,"name":"BitJob","trading":{"WETH":{"volume":"440.00012114","highPrice":"1.06648642","lowPrice":"1.15204499","change24Hour":"-62.26","lastPrice":"0.97957343"}}},{"address":"0x6fc759822056c4645bd52072ce7deb954b40cd5e","symbol":"DNT","decimals":18,"name":"district0x","trading":{"WETH":{"volume":"353.72215673","highPrice":"1.57969962","lowPrice":"1.46096646","change24Hour":"-43.16","lastPrice":"1.41751878"},"DAI":{"volume":"19.33367038","highPrice":"1.63886555","lowPrice":"1.06194189","change24Hour":"62.66","lastPrice":"0.10560237"}}},{"address":"0x634a2fb59f5eeaf5203a0c04eb7e189aa32d4b7e","symbol":"DATA","decimals":18,"name":"Streamr DATAcoin","trading":{"WETH":{"volume":"412.19469684","highPrice":"1.16154386","lowPrice":"1.94100407","change24Hour":"40.98","lastPrice":"0.11703277"},"DAI":{"volume":"301.40683765","highPrice":"1.90409831","lowPrice":"0.02949024","change24Hour":"-25.08","lastPrice":"1.09559589"}}},{"address":"0xdcb9a1bfd87535c4c8581990f2e7600a1b31a317","symbol":"BAT","decimals":18,"name":"Basic Attention Token","trading":{"WETH":{"volume":"258.22099298","highPrice":"0.77336759","lowPrice":"1.65354267","change24Hour":"9.82","lastPrice":"1.28272111"},"DAI":{"volume":"120.69947447","highPrice":"0.28029293","lowPrice":"0.55662471","change24Hour":"-52.69","lastPrice":"0.68549004"}}},{"address":"0x8c6c712c95104d75d6bff672d87e98d2e0c701c1","symbol":"POE","decimals":8,"name":"Po.et","trading":{"WETH":{"volume":"281.71004728","highPrice":"1.91567754","lowPrice":"0.55764992","change24Hour":"23.56","lastPrice":"1.36218329"}}},{"address":"0x6b06f6947e8d74a2ba67437733dd982852e5bee4","symbol":"MANA","decimals":18,"name":"Decentraland MANA","trading":{"WETH":{"volume":"119.70602593","highPrice":"1.14812559","lowPrice":"0.72652930","change24Hour":"23.37","lastPrice":"1.42704007"},"DAI":{"volume":"190.03437296","highPrice":"0.55662734","lowPrice":"1.81991359","change24Hour":"-64.11","lastPrice":"1.14727865"}}},{"address":"0x134d52d8e5ce4effdb262f33437164096f8af867","symbol":"BLT","decimals":18,"name":"Bloom","trading":{"WETH":{"volume":"479.39666291","highPrice":"0.09354071","lowPrice":"0.74394987","change24Hour":"-18.50","lastPrice":"1.14363403"},"DAI":{"volume":"90.16057511","highPrice":"0.48924622","lowPrice":"0.56610997","change24Hour":"55.50","lastPrice":"0.62183600"}}},{"address":"0xda30f50ed2290668df987f07771d01d67d979b9d","symbol":"QVT","decimals":18,"name":"Qvolta","trading":{"WETH":{"volume":"383.56930251","highPrice":"1.27455408","lowPrice":"0.84135312","change24Hour":"61.96","lastPrice":"1.14057117"},"DAI":{"volume":"474.88496581","highPrice":"1.70548865","lowPrice":"1.52435921","change24Hour":"-4.53","lastPrice":"0.29762305"}}},{"address":"0x2b2839013be6ed605661abad8a230aaa943b15ae","symbol":"SUB","decimals":2,"name":"Substratum","trading":{"WETH":{"volume":"189.71363804","highPrice":"1.05055123","lowPrice":"0.89276694","change24Hour":"25.50","lastPrice":"0.03741961"},"DAI":{"volume":"11.53928134","highPrice":"1.98288055","lowPrice":"0.10978080","change24Hour":"-39.16","lastPrice":"1.99388200"}}},{"address":"0x3aadc1fb2488e6f2652cf36d04a214daeecdb3a8","symbol":"GRID","decimals":12,"name":"Grid+","trading":{"WETH":{"volume":"203.40925350","highPrice":"0.87956886","lowPrice":"1.16999373","change24Hour":"-8.49","lastPrice":"0.58287857"},"DAI":{"volume":"258.45809514","highPrice":"1.46975794","lowPrice":"1.15373018","change24Hour":"-36.75","lastPrice":"0.54367036"}}},{"address":"0x6acfbecebc880aa030116b442871b5587958252d","symbol":"CFI","decimals":18,"name":"Cofound.it","trading":{"WETH":{"volume":"23.92857917","highPrice":"0.22412231","lowPrice":"0.93424749","change24Hour":"-52.89","lastPrice":"0.60373522"},"DAI":{"volume":"437.25448393","highPrice":"0.22837453","lowPrice":"0.67672336","change24Hour":"45.24","lastPrice":"0.43023201"}}},{"address":"0xd143797953aca20a5fab1f299a0f0e73c8075eac","symbol":"NMR","decimals":18,"name":"Numeraire","trading":{"WETH":{"volume":"134.34916036","highPrice":"0.98342150","lowPrice":"0.22629480","change24Hour":"43.53","lastPrice":"0.76484611"},"DAI":{"volume":"230.48593232","highPrice":"0.02098358","lowPrice":"1.92719058","change24Hour":"-49.67","lastPrice":"1.19590442"}}},{"address":"0x89d0ab59218b3c0ca5b0f0bf011f25446bf25870","symbol":"CDT","decimals":18,"name":"Coindash","trading":{"WETH":{"volume":"358.08477085","highPrice":"1.06355442","lowPrice":"0.14566344","change24Hour":"35.38","lastPrice":"0.35764609"},"DAI":{"volume":"243.55098756","highPrice":"0.83871772","lowPrice":"0.32256254","change24Hour":"14.42","lastPrice":"1.89648900"}}},{"address":"0x76431c024d5e67ee5f814ce0a422fc6f119de841","symbol":"UKG","decimals":18,"name":"Unikoin Gold","trading":{"WETH":{"volume":"329.07285146","highPrice":"1.15103985","lowPrice":"1.79957415","change24Hour":"-44.82","lastPrice":"1.91162875"},"DAI":{"volume":"366.02129147","highPrice":"1.79755609","lowPrice":"0.91112963","change24Hour":"35.82","lastPrice":"0.59715621"}}},{"address":"0x3ba01c8b016f3ad47411250092fe542f3e6d0ff8","symbol":"RDN","decimals":18,"name":"Raiden","trading":{"WETH":{"volume":"245.31806086","highPrice":"1.10172444","lowPrice":"1.07244067","change24Hour":"-54.16","lastPrice":"1.88116580"},"DAI":{"volume":"195.50146081","highPrice":"1.98837364","lowPrice":"1.80831856","change24Hour":"31.37","lastPrice":"0.25637245"}}},{"address":"0x555a1c96f53951b12ef79d3dfdc834167e5a1ef0","symbol":"KICK","decimals":8,"name":"KickCoin","trading":{"WETH":{"volume":"81.88069285","highPrice":"0.53890194","lowPrice":"1.81765319","change24Hour":"53.75","lastPrice":"0.18667438"},"DAI":{"volume":"478.28067013","highPrice":"0.71821218","lowPrice":"0.34738187","change24Hour":"29.26","lastPrice":"0.77003269"}}},{"address":"0xed081364a3f5556efc9eda8c4858002cb42d8a24","symbol":"AIR","decimals":8,"name":"AirToken","trading":{"WETH":{"volume":"487.48330132","highPrice":"0.71914555","lowPrice":"1.80326034","change24Hour":"-39.49","lastPrice":"0.61792318"},"DAI":{"volume":"237.47834843","highPrice":"0.65886344","lowPrice":"1.58492555","change24Hour":"22.07","lastPrice":"0.07061495"}}},{"address":"0xfa8458eb82b5c3dda991f4b6c274e02b6bd84155","symbol":"WAND","decimals":18,"name":"WandX","trading":{"WETH":{"volume":"41.44638078","highPrice":"0.28293883","lowPrice":"1.01153939","change24Hour":"-58.33","lastPrice":"0.88771623"},"DAI":{"volume":"235.19209353","highPrice":"0.65411132","lowPrice":"0.71497967","change24Hour":"-19.90","lastPrice":"0.38423236"}}},{"address":"0x0d68e37ee7ef6ca1b9bff392ec1e6ebdadcd6dd8","symbol":"VEE","decimals":18,"name":"BLOCKv","trading":{"WETH":{"volume":"147.80561940","highPrice":"1.55545361","lowPrice":"1.00004318","change24Hour":"-55.75","lastPrice":"0.58051270"}}},{"address":"0x59d7689045bfc4147511ccd5ad312e02451e4b93","symbol":"DENT","decimals":8,"name":"DENT","trading":{"WETH":{"volume":"327.90809346","highPrice":"1.02962076","lowPrice":"1.66702812","change24Hour":"50.68","lastPrice":"0.81904923"},"DAI":{"volume":"371.33616302","highPrice":"1.57430967","lowPrice":"0.96182298","change24Hour":"-41.76","lastPrice":"1.51252268"}}},{"address":"0x2bf91b31fa91ae3f5c5c6d25b02a55afc27b0cf8","symbol":"MBRS","decimals":0,"name":"Embermine","trading":{"WETH":{"volume":"385.62749233","highPrice":"0.72521238","lowPrice":"0.44882875","change24Hour":"17.38","lastPrice":"1.51264629"},"DAI":{"volume":"334.35418282","highPrice":"1.39076633","lowPrice":"1.39190820","change24Hour":"27.70","lastPrice":"1.94727217"}}},{"address":"0xe7c5712325b0b429f1ee41aaa64596365bb61e43","symbol":"DCL","decimals":3,"name":"DisLedger","trading":{"WETH":{"volume":"215.20154877","highPrice":"1.99768979","lowPrice":"1.14955840","change24Hour":"41.87","lastPrice":"1.74957354"},"DAI":{"volume":"409.90288125","highPrice":"0.61209523","lowPrice":"0.11390007","change24Hour":"5.27","lastPrice":"0.43609267"}}},{"address":"0x3c429bc4e40387aee981b88c8524c2781db60334","symbol":"WAX","decimals":8,"name":"WAX","trading":{"WETH":{"volume":"130.69606421","highPrice":"1.78814766","lowPrice":"0.25235385","change24Hour":"64.48","lastPrice":"1.76344007"},"DAI":{"volume":"0.71388494","highPrice":"0.30086354","lowPrice":"1.39257411","change24Hour":"38.50","lastPrice":"1.88863689"}}},{"address":"0xd765c54f69a79a876577f72c22a644e12d3eaadf","symbol":"RVT","decimals":18,"name":"Rivetz","trading":{"WETH":{"volume":"258.60015606","highPrice":"0.76829556","lowPrice":"1.80223756","change24Hour":"9.39","lastPrice":"0.79454524"}}},{"address":"0xa10c2ddce0c119acfec58970c941843e72ed50f2","symbol":"SALT","decimals":8,"name":"SALT","trading":{"WETH":{"volume":"37.21135854","highPrice":"1.37784830","lowPrice":"0.39127485","change24Hour":"-56.31","lastPrice":"0.34919206"},"DAI":{"volume":"420.24176626","highPrice":"1.81903982","lowPrice":"0.12061687","change24Hour":"41.17","lastPrice":"0.86418823"}}},{"address":"0xbbbed1a8791ccc4b0a33096f1a93e2290dd5a0e9","symbol":"FUN","decimals":8,"name":"FunFair","trading":{"WETH":{"volume":"24.46469734","highPrice":"0.12254031","lowPrice":"1.17840055","change24Hour":"-36.93","lastPrice":"0.20002391"},"DAI":{"volume":"213.43228850","highPrice":"1.23916905","lowPrice":"1.39581085","change24Hour":"-66.63","lastPrice":"1.06527080"}}},{"address":"0xcc06305efc27f8b3e4b518008ff71be4ac64ffa1","symbol":"CVC","decimals":8,"name":"Civic","trading":{"WETH":{"volume":"313.69131152","highPrice":"1.89095460","lowPrice":"1.63378029","change24Hour":"15.03","lastPrice":"0.58409314"}}},{"address":"0x65724b5e4622ab4af5533625b09434f6c406fd5b","symbol":"SPANK","decimals":18,"name":"SpankChain","trading":{"WETH":{"volume":"499.83887724","highPrice":"0.17897481","lowPrice":"1.05409300","change24Hour":"52.14","lastPrice":"0.68746135"},"DAI":{"volume":"243.28418029","highPrice":"1.19968600","lowPrice":"1.89460596","change24Hour":"-49.38","lastPrice":"0.24321304"}}},{"address":"0xa47db5142c33d28d50b4c4aab57bb9d310da62f8","symbol":"SNIP","decimals":18,"name":"Snip","trading":{"WETH":{"volume":"168.13292273","highPrice":"0.63311036","lowPrice":"0.30993706","change24Hour":"-69.94","lastPrice":"0.84066321"}}},{"address":"0x624c7ca9f2947007ddf8803809ff04d6d1822eb6","symbol":"AION","decimals":8,"name":"AION","trading":{"WETH":{"volume":"32.24285133","highPrice":"0.26477589","lowPrice":"0.72944501","change24Hour":"45.34","lastPrice":"1.03333024"},"DAI":{"volume":"313.01577040","highPrice":"1.89454402","lowPrice":"1.15800506","change24Hour":"-41.93","lastPrice":"0.97496649"}}},{"address":"0x4a2f483d0213a8e756d7976a55f0e7d566d0afad","symbol":"XAUR","decimals":8,"name":"Xaurum","trading":{"WETH":{"volume":"116.85922637","highPrice":"0.40381062","lowPrice":"1.98235661","change24Hour":"60.35","lastPrice":"0.14334292"},"DAI":{"volume":"376.55723165","highPrice":"0.71771647","lowPrice":"0.92877569","change24Hour":"16.08","lastPrice":"1.04567765"}}},{"address":"0x08614af15d2fb9dbb3e0feaff852cbc5b2c83c4c","symbol":"FDX","decimals":18,"name":"fidentiaX","trading":{"WETH":{"volume":"432.04406707","highPrice":"0.24962623","lowPrice":"0.12537862","change24Hour":"42.10","lastPrice":"0.93712583"},"DAI":{"volume":"187.74426519","highPrice":"0.17732163","lowPrice":"0.44892397","change24Hour":"29.60","lastPrice":"0.21687419"}}},{"address":"0x25868ec04c8355a3df479078344afa8168e7d1e0","symbol":"XGM","decimals":8,"name":"Xaurum Gamma","trading":{"WETH":{"volume":"174.04690443","highPrice":"0.43431324","lowPrice":"0.38847525","change24Hour":"24.59","lastPrice":"1.14547903"},"DAI":{"volume":"375.41238778","highPrice":"1.60188978","lowPrice":"1.97151019","change24Hour":"-49.54","lastPrice":"1.89538252"}}},{"address":"0xf12d1f23920c0f1e1aacc810e0ff5c098f8a8582","symbol":"CAT","decimals":18,"name":"BlockCAT","trading":{"WETH":{"volume":"155.17566399","highPrice":"1.02446237","lowPrice":"0.98156226","change24Hour":"66.84","lastPrice":"1.25987011"},"DAI":{"volume":"11.61990140","highPrice":"0.17251239","lowPrice":"1.07761108","change24Hour":"-18.93","lastPrice":"1.90181778"}}},{"address":"0xdbc484885f785484bc13e52c52dce216f70dee24","symbol":"POWR","decimals":6,"name":"PowerLedger","trading":{"WETH":{"volume":"11.04321028","highPrice":"0.78270090","lowPrice":"0.69456452","change24Hour":"32.00","lastPrice":"0.20153015"},"DAI":{"volume":"396.34997840","highPrice":"1.16552686","lowPrice":"1.16555181","change24Hour":"31.17","lastPrice":"0.01907001"}}},{"address":"0x8916b916baffb6abc65b9989f6ff5befcd2759ff","symbol":"ETHOS","decimals":8,"name":"Ethos","trading":{"WETH":{"volume":"425.78406516","highPrice":"1.53345760","lowPrice":"0.98043922","change24Hour":"45.04","lastPrice":"0.36244844"},"DAI":{"volume":"399.23946292","highPrice":"1.86440737","lowPrice":"1.70284075","change24Hour":"-17.48","lastPrice":"1.03280607"}}},{"address":"0xb160389de314edfcd15b9c2a5ffaef23243abb8e","symbol":"INS","decimals":10,"name":"INS","trading":{"WETH":{"volume":"472.51040349","highPrice":"1.42866545","lowPrice":"1.93726485","change24Hour":"64.42","lastPrice":"0.36903260"}}},{"address":"0x77488dc722ba6da94d03c2efaf70bcbe06bf0c0c","symbol":"AE","decimals":18,"name":"Aeternity","trading":{"WETH":{"volume":"83.93397461","highPrice":"1.75107792","lowPrice":"1.45590022","change24Hour":"25.35","lastPrice":"0.69519608"},"DAI":{"volume":"75.73877519","highPrice":"0.36997711","lowPrice":"1.88935281","change24Hour":"23.18","lastPrice":"1.99661191"}}},{"address":"0x82759ebe3b37ff1feee3369d408cb0add172ec85","symbol":"LOC","decimals":18,"name":"Lockchain","trading":{"WETH":{"volume":"468.38505380","highPrice":"1.40990629","lowPrice":"0.95848451","change24Hour":"-29.06","lastPrice":"0.77267013"},"DAI":{"volume":"232.58848453","highPrice":"0.64272165","lowPrice":"1.96377714","change24Hour":"58.14","lastPrice":"0.72956241"}}},{"address":"0x1cf4ecaace3a4c959725886c526686fe412afd45","symbol":"RLC","decimals":9,"name":"iExec","trading":{"WETH":{"volume":"447.41254044","highPrice":"1.62679951","lowPrice":"0.02383909","change24Hour":"-34.32","lastPrice":"1.13374953"}}},{"address":"0xd1b564b3e5cb4ec779af79b3be89bf5d4575ede3","symbol":"ENO","decimals":18,"name":"Ethino","trading":{"WETH":{"volume":"473.73646778","highPrice":"0.21655222","lowPrice":"1.18983217","change24Hour":"-2.52","lastPrice":"1.96233144"},"DAI":{"volume":"136.23990386","highPrice":"0.91698666","lowPrice":"0.06421089","change24Hour":"-18.95","lastPrice":"0.85741189"}}},{"address":"0xb8ac405c5a2ca9692024cdadc9042da3775a2387","symbol":"CRED","decimals":18,"name":"Verify","trading":{"WETH":{"volume":"82.63412246","highPrice":"0.28580491","lowPrice":"1.51694974","change24Hour":"-60.47","lastPrice":"1.21056346"},"DAI":{"volume":"148.07090675","highPrice":"1.30167616","lowPrice":"0.16154596","change24Hour":"-31.48","lastPrice":"0.20245635"}}},{"address":"0x6535b4bc7ddab7653abcac0b3c128eca479f0969","symbol":"GNO","decimals":18,"name":"Gnosis","trading":{"WETH":{"volume":"115.96989538","highPrice":"0.51601436","lowPrice":"1.79555367","change24Hour":"-61.51","lastPrice":"0.07275633"},"DAI":{"volume":"452.51807315","highPrice":"1.34236553","lowPrice":"1.74514960","change24Hour":"-33.46","lastPrice":"1.14115068"}}},{"address":"0xa2dab378ceffb5c3895bebf03936af828ac5f3b0","symbol":"SNT","decimals":18,"name":"StatusNetwork","trading":{"WETH":{"volume":"2.95398151","highPrice":"0.90763593","lowPrice":"0.01002992","change24Hour":"23.41","lastPrice":"1.02824064"},"DAI":{"volume":"328.87792133","highPrice":"1.37396682","lowPrice":"1.19034902","change24Hour":"-5.63","lastPrice":"1.66049306"}}},{"address":"0xeaaa866cbef6d6aef59d08b74f80344e6532b8b4","symbol":"GBT","decimals":18,"name":"HelloGold Gold Backed Token","trading":{"WETH":{"volume":"290.57551874","highPrice":"1.77071010","lowPrice":"1.65256076","change24Hour":"16.32","lastPrice":"1.14935879"},"DAI":{"volume":"201.53599617","highPrice":"0.67449361","lowPrice":"0.81538052","change24Hour":"35.72","lastPrice":"0.02693573"}}},{"address":"0x165c5553649b2b4b7e7ec1590577f10b8167820b","symbol":"IFT","decimals":18,"name":"Investfeed","trading":{"WETH":{"volume":"156.38640837","highPrice":"1.63051450","lowPrice":"0.41048283","change24Hour":"18.28","lastPrice":"1.73448366"},"DAI":{"volume":"68.89563566","highPrice":"1.19705354","lowPrice":"0.73207705","change24Hour":"-67.26","lastPrice":"1.23122301"}}},{"address":"0x0a70c08483e15c0b9d92a32350d91055e203e122","symbol":"GOAL","decimals":18,"name":"Goal Bonanza","trading":{"WETH":{"volume":"20.57950419","highPrice":"0.93219867","lowPrice":"1.78258052","change24Hour":"63.68","lastPrice":"1.43510921"},"DAI":{"volume":"371.55587576","highPrice":"1.16622983","lowPrice":"0.43240774","change24Hour":"20.75","lastPrice":"0.41457924"}}},{"address":"0xa05272199f2fae6f75f7853a3155357079f52c68","symbol":"CAG","decimals":18,"name":"Change Coin","trading":{"WETH":{"volume":"33.77990855","highPrice":"0.00652606","lowPrice":"1.65703245","change24Hour":"19.96","lastPrice":"1.64059108"},"DAI":{"volume":"164.71412894","highPrice":"1.86447783","lowPrice":"0.85534684","change24Hour":"40.75","lastPrice":"0.37800181"}}},{"address":"0xead42f2bcf54cfe24669f72d022abc02df14b32d","symbol":"NEWB","decimals":0,"name":"Newbium","trading":{"WETH":{"volume":"110.45361892","highPrice":"1.40953956","lowPrice":"1.07085533","change24Hour":"-48.53","lastPrice":"0.20936179"},"DAI":{"volume":"209.33474181","highPrice":"1.80075292","lowPrice":"1.70725402","change24Hour":"-46.75","lastPrice":"1.36451818"}}},{"address":"0xe138788f891cff05ce20bc2e2273aa2564a87ad8","symbol":"FYN","decimals":18,"name":"Fundyourself now","trading":{"WETH":{"volume":"411.37511458","highPrice":"1.68058660","lowPrice":"0.78910458","change24Hour":"61.63","lastPrice":"1.14669928"},"DAI":{"volume":"479.22216007","highPrice":"0.69529130","lowPrice":"1.79114546","change24Hour":"68.34","lastPrice":"0.64904924"}}},{"address":"0x90a5ed7f608fc1e7bd3ec223da937a3daa15b234","symbol":"DAI","decimals":18,"name":"Maker DAI","trading":{"WETH":{"volume":"216.10607475","highPrice":"1.95677551","lowPrice":"0.91395824","change24Hour":"-32.52","lastPrice":"1.43449067"}}},{"address":"0x4bd77159468c6d3a0516bf75dcd294647ec0fba8","symbol":"PTOY","decimals":8,"name":"Patientory","trading":{"WETH":{"volume":"210.65833000","highPrice":"0.61416244","lowPrice":"0.05712012","change24Hour":"44.15","lastPrice":"1.85930477"},"DAI":{"volume":"117.37954407","highPrice":"1.96330407","lowPrice":"1.21772499","change24Hour":"-58.21","lastPrice":"0.37083417"}}},{"address":"0xc2fa6af29e03a490fb3d453728103db1b1419e94","symbol":"REQ","decimals":18,"name":"Request Token","trading":{"WETH":{"volume":"109.97737013","highPrice":"0.65922672","lowPrice":"0.63758336","change24Hour":"-39.61","lastPrice":"1.39243990"},"DAI":{"volume":"252.88443326","highPrice":"1.30859402","lowPrice":"0.19897268","change24Hour":"-14.51","lastPrice":"1.17664933"}}},{"address":"0x440229d9c560d48ae212b917276e097f17d02182","symbol":"ANT","decimals":18,"name":"Aragon","trading":{"WETH":{"volume":"365.18863472","highPrice":"0.42497981","lowPrice":"0.46518729","change24Hour":"17.68","lastPrice":"0.99033651"},"DAI":{"volume":"326.65729162","highPrice":"0.74936483","lowPrice":"1.73746293","change24Hour":"42.75","lastPrice":"1.25047296"}}},{"address":"0xad8bb889a9eeae89361f48e39165ce83c77e0cfc","symbol":"QSP","decimals":18,"name":"Quantstamp","trading":{"WETH":{"volume":"284.54588284","highPrice":"1.22863510","lowPrice":"1.79104651","change24Hour":"-42.49","lastPrice":"0.86677026"},"DAI":{"volume":"127.19476910","highPrice":"0.28242761","lowPrice":"1.17673994","change24Hour":"-8.54","lastPrice":"1.32270372"}}},{"address":"0x900a1a5ff81a30db23dfd3ed664f4c87ba3e4aeb","symbol":"FUCK","decimals":4,"name":"Fuck Token","trading":{"WETH":{"volume":"471.00317572","highPrice":"1.23790620","lowPrice":"0.03445013","change24Hour":"-5.86","lastPrice":"1.82480586"},"DAI":{"volume":"196.33781235","highPrice":"1.68439194","lowPrice":"1.17067820","change24Hour":"-31.07","lastPrice":"1.11719518"}}},{"address":"0xd6c2b8e21032cc3ac9199ea97c9d293ade3232b5","symbol":"DOV","decimals":18,"name":"DOVU","trading":{"WETH":{"volume":"125.21660607","highPrice":"1.05222613","lowPrice":"1.96254810","change24Hour":"38.40","lastPrice":"1.61661339"},"DAI":{"volume":"254.31585102","highPrice":"0.73874165","lowPrice":"1.66909444","change24Hour":"-65.20","lastPrice":"1.48943501"}}},{"address":"0x656a16df1cb0ba1931afcb1731067d3d76877214","symbol":"TKR","decimals":18,"name":"Trackr","trading":{"WETH":{"volume":"94.20825401","highPrice":"0.77442534","lowPrice":"1.89868694","change24Hour":"-60.07","lastPrice":"0.97447234"}}},{"address":"0xdc43266229b33826865bfab1552f981433823dbd","symbol":"RPL","decimals":18,"name":"Rocket Pool","trading":{"WETH":{"volume":"158.57468033","highPrice":"0.24322022","lowPrice":"0.08506973","change24Hour":"34.77","lastPrice":"1.88674795"},"DAI":{"volume":"184.18690329","highPrice":"1.04694588","lowPrice":"0.93998569","change24Hour":"-16.29","lastPrice":"1.07282040"}}},{"address":"0x003395426af387f00cd8707fb2e070a5159d708e","symbol":"EVC","decimals":18,"name":"EventChain","trading":{"WETH":{"volume":"93.74186757","highPrice":"1.09342047","lowPrice":"1.51879745","change24Hour":"34.94","lastPrice":"1.20466358"},"DAI":{"volume":"429.16476401","highPrice":"1.12590839","lowPrice":"1.31546276","change24Hour":"29.66","lastPrice":"0.58395005"}}},{"address":"0xcabba946321e354f8cf73a41428ca278d3aed2c1","symbol":"STORJ","decimals":8,"name":"Storj","trading":{"WETH":{"volume":"140.03116882","highPrice":"0.71426428","lowPrice":"0.82820191","change24Hour":"32.88","lastPrice":"0.78692826"}}},{"address":"0x686d73651d0de96a11a7f5398623eb7976488cce","symbol":"HGT","decimals":8,"name":"HelloGold","trading":{"WETH":{"volume":"326.73242095","highPrice":"1.21462722","lowPrice":"1.04090356","change24Hour":"-67.01","lastPrice":"0.97395359"},"DAI":{"volume":"114.22028276","highPrice":"0.91826214","lowPrice":"1.85012451","change24Hour":"25.98","lastPrice":"0.80800236"}}},{"address":"0x86d9fd951c089bc644f48ea6bee3cb56c70411c8","symbol":"ARN","decimals":8,"name":"Aeron","trading":{"WETH":{"volume":"394.80992535","highPrice":"1.87658141","lowPrice":"0.94719950","change24Hour":"24.80","lastPrice":"1.92285771"},"DAI":{"volume":"226.17175418","highPrice":"1.51860762","lowPrice":"1.04478254","change24Hour":"12.99","lastPrice":"1.10740363"}}},{"address":"0x60a387165df969803e2e3e9805fb3eee192ffd19","symbol":"MLN","decimals":18,"name":"Melon Token","trading":{"WETH":{"volume":"94.58812605","highPrice":"0.63440758","lowPrice":"1.05548533","change24Hour":"-26.30","lastPrice":"0.19980517"},"DAI":{"volume":"159.36979407","highPrice":"1.07084043","lowPrice":"0.45890835","change24Hour":"-64.24","lastPrice":"0.82694171"}}},{"address":"0x01c8fdd08343974775c44f278314de32ba1d9e75","symbol":"TAU","decimals":18,"name":"Lamden Tau","trading":{"WETH":{"volume":"219.53218442","highPrice":"0.80616013","lowPrice":"1.63670395","change24Hour":"0.68","lastPrice":"1.19717658"}}},{"address":"0x61dfa0c6602d2efda0b6bcc478f7f6d11abce0cb","symbol":"EQC","decimals":8,"name":"Qchain","trading":{"WETH":{"volume":"107.07785631","highPrice":"1.55108989","lowPrice":"0.21792144","change24Hour":"-7.86","lastPrice":"0.91562569"},"DAI":{"volume":"58.95740515","highPrice":"0.63329233","lowPrice":"0.54853644","change24Hour":"26.72","lastPrice":"0.65097817"}}},{"address":"0x64e932935453a4fff6b2da27df58054204afda6b","symbol":"MKR","decimals":18,"name":"MakerDAO","trading":{"WETH":{"volume":"34.66904396","highPrice":"0.04798897","lowPrice":"1.20967030","change24Hour":"-32.15","lastPrice":"0.53863620"},"DAI":{"volume":"300.22833485","highPrice":"0.54628633","lowPrice":"1.36972691","change24Hour":"-45.97","lastPrice":"0.45901276"}}},{"address":"0x77368801bf46c3b4b9cc60adf51fa9b372c4da6e","symbol":"FLIP","decimals":0,"name":"EtherFlip","trading":{"WETH":{"volume":"181.41588278","highPrice":"0.19181316","lowPrice":"0.22596027","change24Hour":"7.36","lastPrice":"0.41223238"}}},{"address":"0xf32e5f404720e4d00e6d40df3d288c2c83eb4451","symbol":"STORM","decimals":18,"name":"Storm","trading":{"WETH":{"volume":"6.72296585","highPrice":"0.98886243","lowPrice":"1.40876152","change24Hour":"-52.76","lastPrice":"0.54284459"}}},{"address":"0x3e0c724f0e718ab57971866b512eba7787ae4b5f","symbol":"OMG","decimals":18,"name":"OmiseGO","trading":{"WETH":{"volume":"370.44482876","highPrice":"0.06246682","lowPrice":"1.88159949","change24Hour":"4.28","lastPrice":"1.08291912"}}},{"address":"0xadfaa90f93fcaf61ef218382c9f4dd8ad9d42cdd","symbol":"BNTY","decimals":18,"name":"Bounty0x","trading":{"WETH":{"volume":"142.22815237","highPrice":"1.75499142","lowPrice":"1.09575856","change24Hour":"-16.27","lastPrice":"1.09296032"},"DAI":{"volume":"89.73600645","highPrice":"1.03300138","lowPrice":"1.58825117","change24Hour":"33.72","lastPrice":"1.17219533"}}},{"address":"0xc70130ca6ffcf0db237c70951da7ae34f399921b","symbol":"PPT","decimals":8,"name":"Populous","trading":{"WETH":{"volume":"333.43359363","highPrice":"1.74604348","lowPrice":"0.03434581","change24Hour":"-2.23","lastPrice":"1.62201728"},"DAI":{"volume":"213.24485762","highPrice":"1.97892776","lowPrice":"1.79015242","change24Hour":"-17.49","lastPrice":"1.25854944"}}},{"address":"0xe7654404734e7cb0d6bbf69aca50061e37e96cc6","symbol":"DGD","decimals":9,"name":"Digix DAO Token","trading":{"WETH":{"volume":"444.88476415","highPrice":"1.82815770","lowPrice":"0.08687627","change24Hour":"-2.83","lastPrice":"0.33771347"},"DAI":{"volume":"361.53986620","highPrice":"0.74940866","lowPrice":"0.20601904","change24Hour":"58.38","lastPrice":"1.81475568"}}},{"address":"0xfa6d61e7819e6c6409d5f8ca9ec9767dfd906880","symbol":"LNK","decimals":18,"name":"Link Platform","trading":{"WETH":{"volume":"395.28825169","highPrice":"1.22360645","lowPrice":"1.34523700","change24Hour":"-35.45","lastPrice":"1.84237084"},"DAI":{"volume":"3.22102184","highPrice":"1.90354965","lowPrice":"1.77339634","change24Hour":"2.45","lastPrice":"1.66451057"}}},{"address":"0x759ae96bdfa4c971102010f3e6edae567de54ace","symbol":"REP","decimals":18,"name":"Augur Reputation Token","trading":{"WETH":{"volume":"110.11293984","highPrice":"0.14348094","lowPrice":"0.28774779","change24Hour":"-37.28","lastPrice":"0.46781921"},"DAI":{"volume":"446.68858103","highPrice":"0.56553813","lowPrice":"1.09640622","change24Hour":"-63.80","lastPrice":"0.09491246"}}},{"address":"0xfb801d7b41cd3e70a3c60148d6dd62c79f3e50d4","symbol":"TIX","decimals":18,"name":"Blocktix Token","trading":{"WETH":{"volume":"46.51872150","highPrice":"0.56598032","lowPrice":"1.91519764","change24Hour":"57.63","lastPrice":"0.81395452"}}},{"address":"0x9ad98af23fc72f6d8e41359568dd4dc2c5b434cd","symbol":"FUEL","decimals":18,"name":"Ether Party","trading":{"WETH":{"volume":"220.52129044","highPrice":"0.30809344","lowPrice":"1.10769856","change24Hour":"48.50","lastPrice":"0.34771075"}}},{"address":"0x455ebfc401862bc75efcc1d2004d72f7d1c22b60","symbol":"POW","decimals":18,"name":"POWToken","trading":{"WETH":{"volume":"50.96283042","highPrice":"0.76920685","lowPrice":"1.73615292","change24Hour":"2.93","lastPrice":"1.54950487"},"DAI":{"volume":"401.93093731","highPrice":"1.38221422","lowPrice":"0.17715147","change24Hour":"-12.40","lastPrice":"0.98522893"}}},{"address":"0x43af491a7a1c6d37807dfd618e07f5af6ea7991e","symbol":"EBTC","decimals":8,"name":"eBTC","trading":{"WETH":{"volume":"63.98216623","highPrice":"1.03336560","lowPrice":"0.42558597","change24Hour":"50.81","lastPrice":"0.77013635"}}},{"address":"0xc52ce1c6cfebf12628ed7cd7bc7f2aa53176212f","symbol":"MTL","decimals":8,"name":"Metal","trading":{"WETH":{"volume":"483.83393500","highPrice":"0.99969823","lowPrice":"1.52943600","change24Hour":"6.08","lastPrice":"0.81935737"},"DAI":{"volume":"471.26168490","highPrice":"0.99749045","lowPrice":"0.77381619","change24Hour":"-61.46","lastPrice":"0.58182564"}}},{"address":"0xb28fd0b34780c2eecc28875d645e3b64546ee458","symbol":"WLK","decimals":18,"name":"WOLK Token","trading":{"WETH":{"volume":"170.44709960","highPrice":"1.37534371","lowPrice":"1.24204335","change24Hour":"-23.11","lastPrice":"1.65274354"}}},{"address":"0xca8833668f0591ceee59ee2f83b8478377fb0883","symbol":"DGPT","decimals":18,"name":"Digipulse","trading":{"WETH":{"volume":"111.91305611","highPrice":"0.07535535","lowPrice":"0.11336152","change24Hour":"36.32","lastPrice":"0.33147966"}}},{"address":"0x966fcfd5ade551ea741ac6605dbaa37cd8a6966f","symbol":"GUP","decimals":3,"name":"Matchpool","trading":{"WETH":{"volume":"199.78651265","highPrice":"0.35995841","lowPrice":"0.62527828","change24Hour":"44.21","lastPrice":"1.29896656"},"DAI":{"volume":"142.56811002","highPrice":"1.91561974","lowPrice":"1.56977834","change24Hour":"22.93","lastPrice":"1.30682004"}}},{"address":"0x0ac80cfdd08cabec65aba6fa0969b01d4d5d9997","symbol":"RCN","decimals":18,"name":"Ripio Credit Network","trading":{"WETH":{"volume":"220.45185405","highPrice":"0.98364408","lowPrice":"1.54307090","change24Hour":"0.34","lastPrice":"0.17061654"},"DAI":{"volume":"342.76706237","highPrice":"1.70188947","lowPrice":"1.23979528","change24Hour":"58.73","lastPrice":"0.84144402"}}},{"address":"0x11244278596fd446cecda6f057f113fd09d8d6b9","symbol":"ART","decimals":18,"name":"Maecenas","trading":{"WETH":{"volume":"176.67439789","highPrice":"1.55683716","lowPrice":"0.67387163","change24Hour":"64.52","lastPrice":"0.26701758"},"DAI":{"volume":"479.18337770","highPrice":"0.75424270","lowPrice":"1.30322380","change24Hour":"44.13","lastPrice":"0.78311027"}}},{"address":"0x8894767ed0d5181f167f04098d5ddd6c2d83edb1","symbol":"HDG","decimals":18,"name":"Hedge","trading":{"WETH":{"volume":"33.24496606","highPrice":"1.77299616","lowPrice":"1.07522299","change24Hour":"-15.22","lastPrice":"0.10585892"},"DAI":{"volume":"490.59780175","highPrice":"1.84962024","lowPrice":"1.49025426","change24Hour":"-58.38","lastPrice":"1.13639440"}}}]